jenkins.py
jenkins_webapi-0.5.6.dist-info/METADATA
jenkins_webapi-0.5.6.dist-info/RECORD
jenkins_webapi-0.5.6.dist-info/WHEEL
jenkins_webapi-0.5.6.dist-info/top_level.txt
jenkins_webapi-0.5.6.dist-info/zip-safe
